{
  "main": {
    "id": "db0f76e5244ba32a",
    "type": "split",
    "children": [
      {
        "id": "24ac67bace06ab62",
        "type": "tabs",
        "dimension": 51.88042430086789,
        "children": [
          {
            "id": "3e2d43890e417467",
            "type": "leaf",
            "state": {
              "type": "bases",
              "state": {
                "file": "GOD.base",
                "viewName": "Products"
              },
              "icon": "lucide-table",
              "title": "GOD"
            }
          },
          {
            "id": "a61b651c3458f8f2",
            "type": "leaf",
            "state": {
              "type": "markdown",
              "state": {
                "file": "docs/ec/products/編輯商品簡述與商品標語.md",
                "mode": "source",
                "source": true
              },
              "icon": "lucide-file",
              "title": "編輯商品簡述與商品標語"
            }
          },
          {
            "id": "99704a6f7f3446bb",
            "type": "leaf",
            "state": {
              "type": "markdown",
              "state": {
                "file": "docs/ec/products/商品評論指南.md",
                "mode": "source",
                "source": true
              },
              "icon": "lucide-file",
              "title": "商品評論指南"
            }
          },
          {
            "id": "6f44f245f9eec7b4",
            "type": "leaf",
            "state": {
              "type": "markdown",
              "state": {
                "file": "docs/ec/products/編輯商品簡述與商品標語.md",
                "mode": "source",
                "source": true
              },
              "icon": "lucide-file",
              "title": "編輯商品簡述與商品標語"
            }
          },
          {
            "id": "fc6c9ea2d43b17a7",
            "type": "leaf",
            "state": {
              "type": "markdown",
              "state": {
                "file": "docs/ec/products/index.md",
                "mode": "source",
                "source": true
              },
              "icon": "lucide-file",
              "title": "index"
            }
          },
          {
            "id": "8620ce40b4d919c0",
            "type": "leaf",
            "state": {
              "type": "markdown",
              "state": {
                "file": "docs/ec/products/quickstart.md",
                "mode": "source",
                "source": true
              },
              "icon": "lucide-file",
              "title": "quickstart"
            }
          },
          {
            "id": "9b1ddc5234a61de8",
            "type": "leaf",
            "state": {
              "type": "markdown",
              "state": {
                "file": "docs/resources/faq/index.md",
                "mode": "source",
                "source": true
              },
              "icon": "lucide-file",
              "title": "index"
            }
          },
          {
            "id": "00a69bd1bbbad65b",
            "type": "leaf",
            "state": {
              "type": "markdown",
              "state": {
                "file": "docs/resources/glossary.md",
                "mode": "source",
                "source": true
              },
              "icon": "lucide-file",
              "title": "glossary"
            }
          },
          {
            "id": "f35b5b894657b290",
            "type": "leaf",
            "state": {
              "type": "markdown",
              "state": {
                "file": "docs/ec/marketing/index.md",
                "mode": "source",
                "source": true
              },
              "icon": "lucide-file",
              "title": "index"
            }
          },
          {
            "id": "5b3e4a64ff494760",
            "type": "leaf",
            "state": {
              "type": "markdown",
              "state": {
                "file": "docs/ec/products/quickstart.md",
                "mode": "source",
                "source": true
              },
              "icon": "lucide-file",
              "title": "quickstart"
            }
          },
          {
            "id": "a8947af0ce3fc893",
            "type": "leaf",
            "state": {
              "type": "markdown",
              "state": {
                "file": "docs/resources/faq/index.md",
                "mode": "source",
                "source": true
              },
              "icon": "lucide-file",
              "title": "index"
            }
          },
          {
            "id": "35f38d26b9c16f5d",
            "type": "leaf",
            "state": {
              "type": "markdown",
              "state": {
                "file": "docs/ec/products/index.md",
                "mode": "source",
                "source": true
              },
              "icon": "lucide-file",
              "title": "index"
            }
          },
          {
            "id": "9fbbad9c8eb3a655",
            "type": "leaf",
            "state": {
              "type": "markdown",
              "state": {
                "file": "docs/ec/store/index.md",
                "mode": "source",
                "source": true
              },
              "icon": "lucide-file",
              "title": "index"
            }
          },
          {
            "id": "2ca11854d8fb7558",
            "type": "leaf",
            "state": {
              "type": "markdown",
              "state": {
                "file": "docs/resources/faq/使用 Jam 回報問題.md",
                "mode": "source",
                "source": true
              },
              "icon": "lucide-file",
              "title": "使用 Jam 回報問題"
            }
          },
          {
            "id": "1304d920184e0601",
            "type": "leaf",
            "state": {
              "type": "markdown",
              "state": {
                "file": "includes/abbreviations.md",
                "mode": "source",
                "source": true
              },
              "icon": "lucide-file",
              "title": "abbreviations"
            }
          },
          {
            "id": "c69be96320fff845",
            "type": "leaf",
            "state": {
              "type": "markdown",
              "state": {
                "file": "docs/ec/products/quickstart.md",
                "mode": "source",
                "source": true
              },
              "icon": "lucide-file",
              "title": "quickstart"
            }
          },
          {
            "id": "217cb32926a1c0d3",
            "type": "leaf",
            "state": {
              "type": "markdown",
              "state": {
                "file": "includes/abbreviations.md",
                "mode": "source",
                "source": true
              },
              "icon": "lucide-file",
              "title": "abbreviations"
            }
          },
          {
            "id": "a8534256c7f8fa19",
            "type": "leaf",
            "state": {
              "type": "markdown",
              "state": {
                "file": "docs/ec/products/index.md",
                "mode": "source",
                "source": true
              },
              "icon": "lucide-file",
              "title": "index"
            }
          },
          {
            "id": "f2f854fe771505ab",
            "type": "leaf",
            "state": {
              "type": "markdown",
              "state": {
                "file": "docs/ec/products/快速上手商品管理.md",
                "mode": "source",
                "source": true
              },
              "icon": "lucide-file",
              "title": "快速上手商品管理"
            }
          },
          {
            "id": "9a60693b70d0798b",
            "type": "leaf",
            "state": {
              "type": "markdown",
              "state": {
                "file": "includes/abbreviations.md",
                "mode": "source",
                "source": true
              },
              "icon": "lucide-file",
              "title": "abbreviations"
            }
          },
          {
            "id": "c689bd201fe696ec",
            "type": "leaf",
            "state": {
              "type": "markdown",
              "state": {
                "file": "docs/ec/products/index.md",
                "mode": "source",
                "source": true
              },
              "icon": "lucide-file",
              "title": "index"
            }
          },
          {
            "id": "0c0f10dc253c090b",
            "type": "leaf",
            "state": {
              "type": "markdown",
              "state": {
                "file": "docs/ec/marketing/結帳優惠計算順序.md",
                "mode": "source",
                "source": true
              },
              "icon": "lucide-file",
              "title": "結帳優惠計算順序"
            }
          },
          {
            "id": "109de231235ed626",
            "type": "leaf",
            "state": {
              "type": "markdown",
              "state": {
                "file": "docs/ec/products/排除商品上傳至第三方平台.md",
                "mode": "source",
                "source": true
              },
              "icon": "lucide-file",
              "title": "排除商品上傳至第三方平台"
            }
          },
          {
            "id": "76433c3f08d3226a",
            "type": "leaf",
            "state": {
              "type": "markdown",
              "state": {
                "file": "docs/ec/integrations/設定 Google 購物廣告.md",
                "mode": "source",
                "source": true
              },
              "icon": "lucide-file",
              "title": "設定 Google 購物廣告"
            }
          }
        ],
        "currentTab": 13
      },
      {
        "id": "ea951fb7d70bee14",
        "type": "tabs",
        "dimension": 48.11957569913211,
        "children": [
          {
            "id": "5966163e457c587f",
            "type": "leaf",
            "state": {
              "type": "webviewer",
              "state": {
                "url": "https://www.cyberbiz.io/helpcenter/?p=7701",
                "title": "商品管理-商品描述、設定 - CYBERBIZ 一般版教學文件",
                "mode": "webview"
              },
              "icon": "globe-2",
              "title": "商品管理-商品描述、設定 - CYBERBIZ 一般版教學文件"
            }
          },
          {
            "id": "9d592301c67b1ee1",
            "type": "leaf",
            "state": {
              "type": "webviewer",
              "state": {
                "url": "https://www.cyberbiz.io/support/?p=7497",
                "title": "商品管理-商品描述、設定",
                "mode": "webview"
              },
              "icon": "globe-2",
              "title": "商品管理-商品描述、設定"
            }
          },
          {
            "id": "8b169f1b639a04c3",
            "type": "leaf",
            "state": {
              "type": "webviewer",
              "state": {
                "url": "https://www.cyberbiz.io/support/?p=3521",
                "title": "商品標籤管理設定",
                "mode": "webview"
              },
              "icon": "globe-2",
              "title": "商品標籤管理設定"
            }
          },
          {
            "id": "9ddd1b90308bee2b",
            "type": "leaf",
            "state": {
              "type": "webviewer",
              "state": {
                "url": "https://www.cyberbiz.io/support/?p=37330#stock",
                "title": "組合商品",
                "mode": "webview"
              },
              "icon": "globe-2",
              "title": "組合商品"
            }
          }
        ],
        "currentTab": 1
      }
    ],
    "direction": "vertical"
  },
  "left": {
    "id": "5f2449e16eb6824a",
    "type": "split",
    "children": [
      {
        "id": "956d4eee48db551a",
        "type": "tabs",
        "children": [
          {
            "id": "54e462a14a5a6adb",
            "type": "leaf",
            "state": {
              "type": "file-explorer",
              "state": {
                "sortOrder": "alphabetical",
                "autoReveal": false
              },
              "icon": "lucide-folder-closed",
              "title": "Files"
            }
          },
          {
            "id": "536fb88d16f7d477",
            "type": "leaf",
            "state": {
              "type": "search",
              "state": {
                "query": "",
                "matchingCase": false,
                "explainSearch": false,
                "collapseAll": false,
                "extraContext": false,
                "sortOrder": "alphabetical"
              },
              "icon": "lucide-search",
              "title": "Search"
            }
          },
          {
            "id": "8624ad6756c044e3",
            "type": "leaf",
            "state": {
              "type": "bookmarks",
              "state": {},
              "icon": "lucide-bookmark",
              "title": "Bookmarks"
            }
          },
          {
            "id": "b8907fd718bfa751",
            "type": "leaf",
            "state": {
              "type": "notebook-navigator",
              "state": {},
              "icon": "notebook",
              "title": "Notebook Navigator"
            }
          }
        ]
      }
    ],
    "direction": "horizontal",
    "width": 307.5
  },
  "right": {
    "id": "973606ff262c9293",
    "type": "split",
    "children": [
      {
        "id": "cf40cafdac49a724",
        "type": "tabs",
        "children": [
          {
            "id": "29655f1ed2139b13",
            "type": "leaf",
            "state": {
              "type": "outgoing-link",
              "state": {
                "file": "docs/ec/products/index.md",
                "linksCollapsed": false,
                "unlinkedCollapsed": false
              },
              "icon": "links-going-out",
              "title": "Outgoing links from index"
            }
          },
          {
            "id": "ef4268f610d1110b",
            "type": "leaf",
            "state": {
              "type": "tag",
              "state": {
                "sortOrder": "frequency",
                "useHierarchy": true,
                "showSearch": false,
                "searchQuery": ""
              },
              "icon": "lucide-tags",
              "title": "Tags"
            }
          },
          {
            "id": "4b4571c4620c17d1",
            "type": "leaf",
            "state": {
              "type": "outline",
              "state": {
                "file": "docs/ec/products/index.md",
                "followCursor": false,
                "showSearch": false,
                "searchQuery": ""
              },
              "icon": "lucide-list",
              "title": "Outline of index"
            }
          },
          {
            "id": "165974d87f171017",
            "type": "leaf",
            "state": {
              "type": "footnotes",
              "state": {
                "file": "docs/ec/products/index.md"
              },
              "icon": "lucide-file-signature",
              "title": "Footnotes"
            }
          },
          {
            "id": "e137c9afd066bf49",
            "type": "leaf",
            "state": {
              "type": "backlink",
              "state": {
                "file": "docs/resources/index.md",
                "collapseAll": false,
                "extraContext": false,
                "sortOrder": "alphabetical",
                "showSearch": false,
                "searchQuery": "",
                "backlinkCollapsed": false,
                "unlinkedCollapsed": true
              },
              "icon": "links-coming-in",
              "title": "Backlinks for index"
            }
          },
          {
            "id": "2b2d8722c4ab60a4",
            "type": "leaf",
            "state": {
              "type": "smtcmp-chat-view",
              "state": {},
              "icon": "wand-sparkles",
              "title": "Smart composer chat"
            }
          },
          {
            "id": "ee4de6e4fb7a4876",
            "type": "leaf",
            "state": {
              "type": "git-view",
              "state": {},
              "icon": "git-pull-request",
              "title": "Source Control"
            }
          }
        ],
        "currentTab": 6
      }
    ],
    "direction": "horizontal",
    "width": 300
  },
  "left-ribbon": {
    "hiddenItems": {
      "switcher:Open quick switcher": false,
      "graph:Open graph view": false,
      "canvas:Create new canvas": false,
      "daily-notes:Open today's daily note": false,
      "templates:Insert template": false,
      "command-palette:Open command palette": false,
      "bases:Create new base": false,
      "diagram-zoom-drag:Picker mode": false,
      "smart-composer:Open smart composer": false,
      "pdf-plus:PDF++: Toggle auto-copy": false,
      "pdf-plus:PDF++: Toggle auto-focus": false,
      "pdf-plus:PDF++: Toggle auto-paste": false,
      "obsidian-git:Open Git source control": false,
      "notebook-navigator:Notebook Navigator": false,
      "omnisearch:Omnisearch": false
    }
  },
  "active": "2ca11854d8fb7558",
  "lastOpenFiles": [
    "site/ec/products/設定加價購群組的多國語系名稱/index.html",
    "site/ec/products/設定加價購群組的多國語系名稱",
    "site/ec/products/設定任選折扣群組/index.html",
    "site/ec/products/設定任選折扣群組",
    "site/index 1/index.html",
    "site/index 1",
    "site/ec/store/系統通知設定/index.html",
    "site/ec/store/系統通知設定",
    "site/ec/store/index.html",
    "site/ec/store",
    "site/ec/orders/Process C2C Convenience Store Shipments/index.html",
    "docs/resources/faq/index.md",
    "docs/ec/store/index.md",
    "docs/resources/faq/使用 Jam 回報問題.md",
    "docs/ec/products/index.md",
    "templates/lucide-circle-play.md",
    "docs/ec/index.md",
    "includes/abbreviations.md",
    "docs/resources/changelog.md",
    "docs/resources/glossary.md",
    "docs/ec/products/quickstart.md",
    "docs/ec/payments/index.md",
    "docs/ec/orders/index.md",
    "docs/ec/members/index.md",
    "docs/ec/marketing/index.md",
    "docs/ec/integrations/index.md",
    "docs/ec/analytics/index.md",
    "docs/resources/references/商品詳細資訊設定.md",
    "docs/resources/references/文字編輯器使用教學.md",
    "resources/references.md",
    "templates/library.md",
    "templates/lucide-shield.md",
    "templates/syntax-icon-lg.md",
    "templates/lucide-life-buoy.md",
    "docs/ec/products/編輯商品簡述與商品標語.md",
    "docs/ec/products/編輯商品描述與設定.md",
    "site/assets/images/ec-product-brief-n-slogan.zh-tw.png",
    "docs/assets/images/ec-product-brief-n-slogan.zh-tw.png",
    "site/assets/images/ec-product-description-brief-frontend.zh-tw.png",
    "docs/assets/images/ec-product-description-brief-frontend.zh-tw.png",
    "site/assets/images/ec-generate-text-html-syntax.zh-tw.gif",
    "docs/assets/images/ec-generate-text-html-syntax.zh-tw.gif",
    "site/assets/images/ec-product-review-management.zh-tw.png",
    "docs/assets/images/ec-product-review-management.zh-tw.png",
    "ec-product-review-management.zh-tw.png",
    "site/assets/images/ec-3d-secure-flowchart.png"
  ]
}